[
    { "id": 1, "omschrijving": "aardewerk", "parent": null, "hasChildren": true, "type": "PT" },
    { "id": 48, "omschrijving": "aluminium", "parent": 8, "hasChildren": false, "type": "PT" },
    { "id": 33, "omschrijving": "amber", "parent": 32, "hasChildren": false, "type": "PT" },
    { "id": 34, "omschrijving": "barnsteen", "parent": null, "hasChildren": false, "type": "ND", "use": 33 },
    { "id": 38, "omschrijving": "beton", "parent": null, "hasChildren": true, "type": "PT" },
    { "id": 10, "omschrijving": "bladgoud", "parent": 9, "hasChildren": false, "type": "PT" },
    { "id": 23, "omschrijving": "bont", "parent": 21, "hasChildren": false, "type": "PT" },
    { "id": 24, "omschrijving": "botmateriaal", "parent": 21, "hasChildren": true, "type": "PT" },
    { "id": 14, "omschrijving": "brons", "parent": 13, "hasChildren": false, "type": "PT" },
    { "id": 49, "omschrijving": "cement", "parent": null, "hasChildren": false, "type": "PT" },
    { "id": 3, "omschrijving": "ceramiek", "parent": null, "hasChildren": false, "type": "ND", "use": 1 },
    { "id": 25, "omschrijving": "dierlijk botmateriaal", "parent": 24, "hasChildren": false, "type": "PT" },
    { "id": 39, "omschrijving": "gewapend beton", "parent": 38, "hasChildren": false, "type": "PT" },
    { "id": 27, "omschrijving": "gewei", "parent": 21, "hasChildren": false, "type": "PT" },
    { "id": 7, "omschrijving": "glas", "parent": null, "hasChildren": false, "type": "PT" },
    { "id": 9, "omschrijving": "goud", "parent": 8, "hasChildren": true, "type": "PT" },
    { "id": 28, "omschrijving": "hoorn\/hoornpitten", "parent": 21, "hasChildren": false, "type": "PT" },
    { "id": 35, "omschrijving": "hout", "parent": 32, "hasChildren": false, "type": "PT" },
    { "id": 36, "omschrijving": "houtskool", "parent": 32, "hasChildren": false, "type": "PT" },
    { "id": 29, "omschrijving": "huid", "parent": 21, "hasChildren": true, "type": "PT" },
    { "id": 11, "omschrijving": "ijzer", "parent": 8, "hasChildren": false, "type": "PT" },
    { "id": 4, "omschrijving": "keramiek", "parent": null, "hasChildren": false, "type": "ND", "use": 1 },
    { "id": 12, "omschrijving": "koper", "parent": 8, "hasChildren": true, "type": "PT" },
    { "id": 13, "omschrijving": "koperlegeringen", "parent": 12, "hasChildren": true, "type": "PT" },
    { "id": 20, "omschrijving": "kunststof", "parent": null, "hasChildren": false, "type": "PT" },
    { "id": 44, "omschrijving": "kwartsiet van Tienen", "parent": 43, "hasChildren": false, "type": "PT" },
    { "id": 43, "omschrijving": "kwartsitisch lithisch materiaal", "parent": 42, "hasChildren": true, "type": "PT" },
    { "id": 30, "omschrijving": "leer", "parent": 29, "hasChildren": false, "type": "PT" },
    { "id": 42, "omschrijving": "lithisch materiaal", "parent": 40, "hasChildren": true, "type": "PT" },
    { "id": 16, "omschrijving": "lood", "parent": 8, "hasChildren": false, "type": "PT" },
    { "id": 0, "omschrijving": "Materiaal", "parent": null, "hasChildren": true, "type": "HR" },
    { "id": 26, "omschrijving": "menselijk botmateriaal", "parent": 24, "hasChildren": false, "type": "PT" },
    { "id": 15, "omschrijving": "messing", "parent": 13, "hasChildren": false, "type": "PT" },
    { "id": 8, "omschrijving": "metaal", "parent": null, "hasChildren": true, "type": "PT" },
    { "id": 41, "omschrijving": "natuursteen", "parent": 40, "hasChildren": false, "type": "PT" },
    { "id": 21, "omschrijving": "organisch materiaal", "parent": null, "hasChildren": true, "type": "PT" },
    { "id": 2, "omschrijving": "pijpaarde", "parent": 1, "hasChildren": false, "type": "PT" },
    { "id": 32, "omschrijving": "plantaardig materiaal", "parent": 21, "hasChildren": true, "type": "PT" },
    { "id": 50, "omschrijving": "pleister", "parent": null, "hasChildren": false, "type": "PT" },
    { "id": 5, "omschrijving": "porselein", "parent": 1, "hasChildren": false, "type": "PT" },
    { "id": 31, "omschrijving": "schelp", "parent": null, "hasChildren": false, "type": "PT" },
    { "id": 46, "omschrijving": "silex", "parent": 42, "hasChildren": false, "type": "PT" },
    { "id": 17, "omschrijving": "staal", "parent": 8, "hasChildren": false, "type": "PT" },
    { "id": 40, "omschrijving": "steen", "parent": null, "hasChildren": true, "type": "PT" },
    { "id": 6, "omschrijving": "steengoed", "parent": 1, "hasChildren": false, "type": "PT" },
    { "id": 37, "omschrijving": "textiel", "parent": 32, "hasChildren": false, "type": "PT" },
    { "id": 18, "omschrijving": "tin", "parent": 8, "hasChildren": false, "type": "PT" },
    { "id": 47, "omschrijving": "vuursteen", "parent": null, "hasChildren": false, "type": "ND", "use": 46 },
    { "id": 45, "omschrijving": "wommersomkwartsiet", "parent": 43, "hasChildren": false, "type": "PT" },
    { "id": 19, "omschrijving": "zilver", "parent": 8, "hasChildren": false, "type": "PT" }
]